<?xml version="1.0"?>
<opencv_storage>
<stage12>
  <maxWeakCount>27</maxWeakCount>
  <stageThreshold>-1.2433247566223145e+00</stageThreshold>
  <weakClassifiers>
    <_>
      <internalNodes>
        0 -1 2025 -334622723 -40998627 1710751389 -33851054 -918552579
        -41122865 -545792005 1866099246</internalNodes>
      <leafValues>
        -4.0400338172912598e-01 5.9432934969663620e-02</leafValues></_>
    <_>
      <internalNodes>
        0 -1 120 -285498709 1784207275 -423861510 -1428890217 1967645279
        1684295519 1471805413 -136188513</internalNodes>
      <leafValues>
        -2.3540316522121429e-01 2.3245395720005035e-01</leafValues></_>
    <_>
      <internalNodes>
        0 -1 6521 -578993373 260401050 463338810 -1646358025 -544229674
        -272915624 -2051275664 -994453837</internalNodes>
      <leafValues>
        -2.6958760619163513e-01 1.9565908610820770e-01</leafValues></_>
    <_>
      <internalNodes>
        0 -1 3508 -254840399 909163576 234356433 -1750236395 636421175
        -1934672231 -554734567 -99628420</internalNodes>
      <leafValues>
        -1.6416841745376587e-01 3.0696439743041992e-01</leafValues></_>
    <_>
      <internalNodes>
        0 -1 7878 643979255 -1967114256 -1089938749 -1616746160
        -1359927935 -1930240374 1335230459 -861938279</internalNodes>
      <leafValues>
        -2.4546179175376892e-01 2.0482796430587769e-01</leafValues></_>
    <_>
      <internalNodes>
        0 -1 203 585428511 2104605712 1091469661 1632976241 585371084
        -1725638348 247573647 201661809</internalNodes>
      <leafValues>
        -3.3044493198394775e-01 1.4000980556011200e-01</leafValues></_>
    <_>
      <internalNodes>
        0 -1 7379 1435464962 -115477549 2031808368 -32316591 1815679899
        -1203994309 1030471542 1144206731</internalNodes>
      <leafValues>
        -2.4686579406261444e-01 2.0279555022716522e-01</leafValues></_>
    <_>
      <internalNodes>
        0 -1 7081 -1106994767 -1112131404 -1073791619 -1074843660
        -1430611559 -807207443 -46264583 -1895872260</internalNodes>
      <leafValues>
        -1.8333128094673157e-01 2.6897826790809631e-01</leafValues></_>
    <_>
      <internalNodes>
        0 -1 4779 -69071499 -128970275 -355910241 185375773 -1736881712
        -656646833 -1143995654 -33420726</internalNodes>
      <leafValues>
        -2.3427225649356842e-01 2.0500062406063080e-01</leafValues></_>
    <_>
      <internalNodes>
        0 -1 6680 1386509544 -797784815 840105148 -481122801 328799454
        -75911530 1763900410 770559914</internalNodes>
      <leafValues>
        -2.5088548660278320e-01 1.9964483380317688e-01</leafValues></_>
    <_>
      <internalNodes>
        0 -1 3383 1443233536 496494007 -1266091584 1065528064 169626535
        146440781 -1105118676 868852234</internalNodes>
      <leafValues>
        -3.0392631888389587e-01 1.6997960209846497e-01</leafValues></_>
    <_>
      <internalNodes>
        0 -1 7818 216609584 -1936672172 600530809 -1615054016 675114636
        -1158662480 1137525085 -1901520292</internalNodes>
      <leafValues>
        -3.5362774133682251e-01 1.2446779757738113e-01</leafValues></_>
    <_>
      <internalNodes>
        0 -1 8434 -436499966 172455181 -1972273152 1922982291
        -1067204604 165957645 1927411492 -1829507586</internalNodes>
      <leafValues>
        -3.0148941278457642e-01 1.7614606022834778e-01</leafValues></_>
    <_>
      <internalNodes>
        0 -1 8118 -1027727273 1919837535 2055035832 -1186301406
        -1493418796 -1082524428 -26858050 -1355919816</internalNodes>
      <leafValues>
        -2.0727446675300598e-01 2.5034043192863464e-01</leafValues></_>
    <_>
      <internalNodes>
        0 -1 377 -2143556061 -684903210 -1541764992 -1930665585
        1703361377 1052930225 2027808372 1924379873</internalNodes>
      <leafValues>
        -2.5399819016456604e-01 2.1103966236114502e-01</leafValues></_>
    <_>
      <internalNodes>
        0 -1 5254 541067792 -1464855760 2089387176 -1150377014
        1369071728 2099355747 -126845523 14438952</internalNodes>
      <leafValues>
        -5.8638781309127808e-01 6.3681796193122864e-02</leafValues></_>
    <_>
      <internalNodes>
        0 -1 3093 -670906222 520988124 -930427151 -1217313428 -667753572
        1895315873 680536731 1582823506</internalNodes>
      <leafValues>
        -2.5041306018829346e-01 2.0540343225002289e-01</leafValues></_>
    <_>
      <internalNodes>
        0 -1 721 -364952793 134377506 -924293412 -1408874437 -627361788
        -549433814 -790451429 1949519431</internalNodes>
      <leafValues>
        -3.2270812988281250e-01 1.6533243656158447e-01</leafValues></_>
    <_>
      <internalNodes>
        0 -1 8402 1526715008 1309181629 618356825 -7343322 -1324547429
        -963985295 -791198460 -2138581002</internalNodes>
      <leafValues>
        -2.5206288695335388e-01 2.1197764575481415e-01</leafValues></_>
    <_>
      <internalNodes>
        0 -1 7974 -972137352 646649672 -1160540144 -2051939160 473124848
        714962976 -1997246008 -1932791382</internalNodes>
      <leafValues>
        -2.5405952334403992e-01 2.0932209491729736e-01</leafValues></_>
    <_>
      <internalNodes>
        0 -1 9 -2097624026 2011937310 1149845175 -271588551 -40323925
        1840980324 1708562869 2071030884</internalNodes>
      <leafValues>
        -2.7113294601440430e-01 1.9809585809707642e-01</leafValues></_>
    <_>
      <internalNodes>
        0 -1 4769 1726393366 514329379 -99454404 934200572 -625181420
        453135074 1835289816 -1631889804</internalNodes>
      <leafValues>
        -2.9810115694999695e-01 1.7891080677509308e-01</leafValues></_>
    <_>
      <internalNodes>
        0 -1 389 -408165706 1921150112 75924649 606798642 907138656
        2120765682 340255521 1275491894</internalNodes>
      <leafValues>
        -3.4038341045379639e-01 1.7095522582530975e-01</leafValues></_>
    <_>
      <internalNodes>
        0 -1 2922 2061662087 1060223657 -52331 -809672909 -1551167081
        -1612003674 -805911125 -541071409</internalNodes>
      <leafValues>
        -1.3687606155872345e-01 3.9521968364715576e-01</leafValues></_>
    <_>
      <internalNodes>
        0 -1 3436 1212204941 937087107 1348272213 817027144 1192981431
        1071868773 -2050872449 -211288794</internalNodes>
      <leafValues>
        -2.3906692862510681e-01 2.2729639708995819e-01</leafValues></_>
    <_>
      <internalNodes>
        0 -1 6901 -1008824943 1142553763 -1559601409 -235963174
        135191612 296691663 883124484 -321010845</internalNodes>
      <leafValues>
        -2.5414973497390747e-01 2.1805462241172791e-01</leafValues></_>
    <_>
      <internalNodes>
        0 -1 4391 673941554 95200491 -428518267 -2036911929 1950978547
        835729114 1177677358 1074535952</internalNodes>
      <leafValues>
        -4.0132516622543335e-01 1.3881337642669678e-01</leafValues></_></weakClassifiers></stage12>
</opencv_storage>
