<?xml version="1.0"?>
<opencv_storage>
<stage11>
  <maxWeakCount>26</maxWeakCount>
  <stageThreshold>-1.1004357337951660e+00</stageThreshold>
  <weakClassifiers>
    <_>
      <internalNodes>
        0 -1 1436 -17150857 -62441 -513419329 1599991679 -314060820
        -1158800523 -26041665 -82642305</internalNodes>
      <leafValues>
        -3.3143785595893860e-01 1.8201658129692078e-01</leafValues></_>
    <_>
      <internalNodes>
        0 -1 8014 -626018400 -772603945 1505222133 -201459779
        -1258846293 380562082 -1459629681 -2132824691</internalNodes>
      <leafValues>
        -2.2604839503765106e-01 2.4246895313262939e-01</leafValues></_>
    <_>
      <internalNodes>
        0 -1 1 -962418037 -1935451213 -225378357 -1083537613 2063016295
        662773606 -970607868 1615922481</internalNodes>
      <leafValues>
        -2.8469496965408325e-01 1.8312595784664154e-01</leafValues></_>
    <_>
      <internalNodes>
        0 -1 8004 688377617 -9837198 1874328679 -5529612 792689443
        -273682527 -1892155529 -541600283</internalNodes>
      <leafValues>
        -1.9666320085525513e-01 2.5940778851509094e-01</leafValues></_>
    <_>
      <internalNodes>
        0 -1 3605 1078350798 -110149686 937737131 933806068 387048413
        1560844010 -328655153 600419214</internalNodes>
      <leafValues>
        -1.9556613266468048e-01 2.6201832294464111e-01</leafValues></_>
    <_>
      <internalNodes>
        0 -1 7995 -1430601839 529813176 -211069641 -920148 770992605
        -1563823623 1560941692 -1179431496</internalNodes>
      <leafValues>
        -2.6699826121330261e-01 1.9119019806385040e-01</leafValues></_>
    <_>
      <internalNodes>
        0 -1 6347 -35426644 483688456 475799771 227779851 -136175620
        521672192 1969592123 784023423</internalNodes>
      <leafValues>
        -2.7553397417068481e-01 1.8401092290878296e-01</leafValues></_>
    <_>
      <internalNodes>
        0 -1 130 235053586 2100223836 747122388 1113778678 -2127173967
        958054497 1502962657 1081434674</internalNodes>
      <leafValues>
        -3.9323094487190247e-01 1.1110953986644745e-01</leafValues></_>
    <_>
      <internalNodes>
        0 -1 8141 -183505408 -2136553588 215188736 -2133131429
        1749746368 1101568510 1725914144 4321703</internalNodes>
      <leafValues>
        -3.7997177243232727e-01 1.5699866414070129e-01</leafValues></_>
    <_>
      <internalNodes>
        0 -1 6912 2010847167 -143577040 -1915273541 -915199197 682461881
        -1075421577 115715263 -204091717</internalNodes>
      <leafValues>
        -1.7925089597702026e-01 3.1669121980667114e-01</leafValues></_>
    <_>
      <internalNodes>
        0 -1 60 1145546808 1089194319 -668643242 1279899330 1563422715
        -901019637 -109320470 4222992</internalNodes>
      <leafValues>
        -3.8892659544944763e-01 1.5003107488155365e-01</leafValues></_>
    <_>
      <internalNodes>
        0 -1 5495 1928560437 923873161 2142418943 -4917258 234840309
        -1612886804 -575403761 -1184501969</internalNodes>
      <leafValues>
        -2.0465265214443207e-01 2.8419801592826843e-01</leafValues></_>
    <_>
      <internalNodes>
        0 -1 6312 -649794420 -785088508 -1969962020 67141148 1218134234
        1012110135 1892756159 156063098</internalNodes>
      <leafValues>
        -2.9040300846099854e-01 2.0075580477714539e-01</leafValues></_>
    <_>
      <internalNodes>
        0 -1 3208 1995850247 1014892390 -1365443466 795900422 1482838124
        -108378036 1580871400 -1416471789</internalNodes>
      <leafValues>
        -3.0618521571159363e-01 1.6304543614387512e-01</leafValues></_>
    <_>
      <internalNodes>
        0 -1 2800 -617429985 -851580055 1828564693 2122136639 -831130623
        -604145801 -412820034 -29107106</internalNodes>
      <leafValues>
        -1.5437030792236328e-01 3.2611712813377380e-01</leafValues></_>
    <_>
      <internalNodes>
        0 -1 8181 -3410525 786625393 1214902512 -271735468 -1391761893
        -1465914246 1450465286 -929240410</internalNodes>
      <leafValues>
        -2.2776024043560028e-01 2.4946352839469910e-01</leafValues></_>
    <_>
      <internalNodes>
        0 -1 6467 503384368 -802001121 1171729012 1965922162 880505064
        -1401760911 289524317 1403140</internalNodes>
      <leafValues>
        -3.9769479632377625e-01 1.2620475888252258e-01</leafValues></_>
    <_>
      <internalNodes>
        0 -1 7023 1998637250 -234823230 -981609234 -1783485760
        1255086221 1066265489 1121212658 688721475</internalNodes>
      <leafValues>
        -2.8821232914924622e-01 1.9414450228214264e-01</leafValues></_>
    <_>
      <internalNodes>
        0 -1 5094 -2119990752 548863652 -1786462544 -139421372
        -716754171 1356983299 340008532 -186608576</internalNodes>
      <leafValues>
        -3.4354358911514282e-01 1.6689975559711456e-01</leafValues></_>
    <_>
      <internalNodes>
        0 -1 5984 -975183358 -1003091218 1020959914 1906764122 316711113
        1794820195 -240433480 -226542013</internalNodes>
      <leafValues>
        -2.5252464413642883e-01 2.3187008500099182e-01</leafValues></_>
    <_>
      <internalNodes>
        0 -1 230 -1402303198 212642776 71708390 1089913797 -613754603
        204356388 1951469847 108089908</internalNodes>
      <leafValues>
        -5.1485091447830200e-01 1.1855877935886383e-01</leafValues></_>
    <_>
      <internalNodes>
        0 -1 3708 -1974203878 524947384 674497844 1070288243 1483494864
        202013652 -665822670 712078546</internalNodes>
      <leafValues>
        -4.0027371048927307e-01 1.3891959190368652e-01</leafValues></_>
    <_>
      <internalNodes>
        0 -1 6618 -547626509 454094674 1325366759 958595057 2058233604
        746016287 -307742612 -341061777</internalNodes>
      <leafValues>
        -2.0291213691234589e-01 2.9435700178146362e-01</leafValues></_>
    <_>
      <internalNodes>
        0 -1 3040 243967280 -1093633940 -1530575747 -2905696 1176753913
        -1632183347 674831549 -1009013755</internalNodes>
      <leafValues>
        -2.3754875361919403e-01 2.4349018931388855e-01</leafValues></_>
    <_>
      <internalNodes>
        0 -1 7972 -876924758 35265525 1317829120 751727700 -1452710718
        1277620355 2021738613 -1936069221</internalNodes>
      <leafValues>
        -3.1800577044487000e-01 1.8439888954162598e-01</leafValues></_>
    <_>
      <internalNodes>
        0 -1 6069 -699387176 949141576 -1215678883 -1111977576
        1427656692 -1919110976 -859811863 -1140827216</internalNodes>
      <leafValues>
        -2.7345001697540283e-01 2.0627680420875549e-01</leafValues></_></weakClassifiers></stage11>
</opencv_storage>
